jxrd_stock_strategy_pkg/__init__.py
jxrd_stock_strategy_pkg/colors.py
jxrd_stock_strategy_pkg/number_utils.py
jxrd_stock_strategy_pkg/params.py
jxrd_stock_strategy_pkg/strategy.py
jxrd_stock_strategy_pkg/strategy_stub.py
jxrd_stock_strategy_pkg/time_utils.py
jxrd_futures_strategy-0.8.6.dist-info/METADATA
jxrd_futures_strategy-0.8.6.dist-info/WHEEL
jxrd_futures_strategy-0.8.6.dist-info/top_level.txt
jxrd_futures_strategy-0.8.6.dist-info/RECORD
